AUTHORS
LICENSE
README.md
setup.py
venus/__init__.py
venus/__main__.py
venus/venus.py
venus/os_tools/darwin.py
venus/os_tools/linux.py
venus/os_tools/windows.py
venuspy.egg-info/PKG-INFO
venuspy.egg-info/SOURCES.txt
venuspy.egg-info/dependency_links.txt
venuspy.egg-info/entry_points.txt
venuspy.egg-info/requires.txt
venuspy.egg-info/top_level.txt