Metadata-Version: 2.1
Name: venuspy
Version: 1.0.4
Summary: A cross platform tool for setting a random wallpaper image from unsplash.com
Home-page: https://github.com/AlfredoSequeida/venus
Author: Alfredo Sequeida
License: MIT
Download-URL: https://github.com/AlfredoSequeida/venus/archive/1.0.4.tar.gz
Keywords: wallpaper unsplash randomwallpaper
Platform: any
Classifier: Intended Audience :: End Users/Desktop
Classifier: License :: OSI Approved :: MIT License
Classifier: Programming Language :: Python :: 3
Classifier: Programming Language :: Python :: 3.4
Classifier: Programming Language :: Python :: 3.5
Classifier: Programming Language :: Python :: 3.6
Classifier: Programming Language :: Python :: 3.7
Classifier: Programming Language :: Python :: 3.8
Classifier: Programming Language :: Python :: 3.9
Classifier: Programming Language :: Python :: 3.10
Classifier: Operating System :: Microsoft :: Windows :: Windows 10
Classifier: Operating System :: Microsoft :: Windows :: Windows 8
Classifier: Operating System :: Microsoft :: Windows :: Windows 8.1
Classifier: Operating System :: MacOS :: MacOS X
Classifier: Operating System :: POSIX :: Linux
Classifier: Topic :: Desktop Environment
License-File: LICENSE
License-File: AUTHORS
